nativetypes/__init__.py
nativetypes/native_float.py
nativetypes/native_int.py
nativetypes-1.0.7.dist-info/LICENSE
nativetypes-1.0.7.dist-info/METADATA
nativetypes-1.0.7.dist-info/WHEEL
nativetypes-1.0.7.dist-info/top_level.txt
nativetypes-1.0.7.dist-info/RECORD
