Metadata-Version: 2.1
Name: nativetypes
Version: 1.0.7
Summary: Native integer and floating-point type emulation
Home-page: https://github.com/AlexAltea/ntypes
Author: Alexandro Sanchez Bach
Author-email: alexandro@phi.nz
License: MIT
Download-URL: https://github.com/AlexAltea/ntypes/tarball/1.0.7
Platform: UNKNOWN
Classifier: Intended Audience :: Developers
Classifier: License :: OSI Approved :: MIT License
Classifier: Programming Language :: Python :: 3.7
Classifier: Programming Language :: Python :: 3.8
Classifier: Programming Language :: Python :: 3.9
Classifier: Programming Language :: Python :: 3.10
Classifier: Programming Language :: Python :: 3.11
Classifier: Programming Language :: Python :: 3.12
Classifier: Natural Language :: English
License-File: LICENSE
